{
  "schemaVersion": 1,
  "generatedAt": "2026-01-28",
  "root": "cat-engine",
  "notes": [
    "This is a lightweight dependency graph derived from explicit Rust module imports (use statements), field ownership, and direct cross-system calls.",
    "It is not a full call graph; edges are intended to describe architectural dependencies between engine subsystems."
  ],
  "nodes": [
    { "id": "engine::Universe", "kind": "engine", "path": "src/engine/universe.rs" },
    { "id": "engine::Windowing", "kind": "engine", "path": "src/engine/windowing.rs" },
    { "id": "engine::user_input::UserInput", "kind": "engine", "path": "src/engine/user_input.rs" },
    { "id": "engine::user_input::InputState", "kind": "engine", "path": "src/engine/user_input.rs" },

    { "id": "ecs::World", "kind": "ecs_core", "path": "src/engine/ecs/mod.rs" },
    { "id": "ecs::CommandQueue", "kind": "ecs_core", "path": "src/engine/ecs/command_queue.rs" },
    { "id": "ecs::SystemWorld", "kind": "ecs_core", "path": "src/engine/ecs/system/system_world.rs" },

    { "id": "ecs::system::TransformSystem", "kind": "ecs_system", "path": "src/engine/ecs/system/transform_system.rs" },
    { "id": "ecs::system::CameraSystem", "kind": "ecs_system", "path": "src/engine/ecs/system/camera_system.rs" },
    { "id": "ecs::system::InputSystem", "kind": "ecs_system", "path": "src/engine/ecs/system/input_system.rs" },
    { "id": "ecs::system::LightSystem", "kind": "ecs_system", "path": "src/engine/ecs/system/light_system.rs" },
    { "id": "ecs::system::RenderableSystem", "kind": "ecs_system", "path": "src/engine/ecs/system/renderable_system.rs" },
    { "id": "ecs::system::TextureSystem", "kind": "ecs_system", "path": "src/engine/ecs/system/texture_system.rs" },
    { "id": "ecs::system::TextSystem", "kind": "ecs_system", "path": "src/engine/ecs/system/text_system.rs" },
    { "id": "ecs::system::GLTFSystem", "kind": "ecs_system", "path": "src/engine/ecs/system/gltf_system.rs" },
    { "id": "ecs::system::OpenXRSystem", "kind": "ecs_system", "path": "src/engine/ecs/system/openxr_system.rs" },
    { "id": "ecs::system::CollisionSystem", "kind": "ecs_system", "path": "src/engine/ecs/system/collision_system.rs" },

    { "id": "graphics::VisualWorld", "kind": "graphics", "path": "src/engine/graphics/visual_world.rs" },
    { "id": "graphics::RenderAssets", "kind": "graphics", "path": "src/engine/graphics/render_assets.rs" },
    { "id": "graphics::VulkanoRenderer", "kind": "graphics", "path": "src/engine/graphics/vulkano_renderer.rs" },
    { "id": "graphics::primitives", "kind": "graphics", "path": "src/engine/graphics/primitives.rs" },
    { "id": "graphics::mesh", "kind": "graphics", "path": "src/engine/graphics/mesh.rs" },
    { "id": "graphics::XRSwapchain", "kind": "graphics", "path": "src/engine/graphics/xr_swapchain.rs" },
    { "id": "graphics::XrVulkanGraphics", "kind": "graphics", "path": "src/engine/graphics/mod.rs" },

    { "id": "utils::math", "kind": "utils", "path": "src/utils/mod.rs" }
  ],
  "edges": [
    { "from": "engine::Windowing", "to": "engine::Universe", "kind": "uses", "via": "run_app() stores and drives Universe" },
    { "from": "engine::Windowing", "to": "engine::user_input::UserInput", "kind": "uses", "via": "winit events -> UserInput" },

    { "from": "engine::Universe", "to": "ecs::World", "kind": "owns", "via": "Universe.world" },
    { "from": "engine::Universe", "to": "ecs::CommandQueue", "kind": "owns", "via": "Universe.command_queue" },
    { "from": "engine::Universe", "to": "ecs::SystemWorld", "kind": "owns", "via": "Universe.systems" },
    { "from": "engine::Universe", "to": "graphics::VisualWorld", "kind": "owns", "via": "Universe.visuals" },
    { "from": "engine::Universe", "to": "graphics::RenderAssets", "kind": "owns", "via": "Universe.render_assets" },
    { "from": "engine::Universe", "to": "graphics::VulkanoRenderer", "kind": "owns", "via": "Universe.renderer" },
    { "from": "engine::Universe", "to": "engine::user_input::InputState", "kind": "uses", "via": "Universe.update(dt, input)" },

    { "from": "ecs::CommandQueue", "to": "ecs::SystemWorld", "kind": "calls", "via": "flush() dispatches to systems.*" },
    { "from": "ecs::CommandQueue", "to": "ecs::World", "kind": "uses", "via": "flush(world, systems, visuals)" },
    { "from": "ecs::CommandQueue", "to": "graphics::VisualWorld", "kind": "uses", "via": "flush(world, systems, visuals)" },

    { "from": "ecs::SystemWorld", "to": "ecs::system::TransformSystem", "kind": "owns", "via": "SystemWorld.transform" },
    { "from": "ecs::SystemWorld", "to": "ecs::system::CollisionSystem", "kind": "owns", "via": "SystemWorld.collision" },
    { "from": "ecs::SystemWorld", "to": "ecs::system::RenderableSystem", "kind": "owns", "via": "SystemWorld.renderable" },
    { "from": "ecs::SystemWorld", "to": "ecs::system::GLTFSystem", "kind": "owns", "via": "SystemWorld.gltf" },
    { "from": "ecs::SystemWorld", "to": "ecs::system::OpenXRSystem", "kind": "owns", "via": "SystemWorld.openxr" },
    { "from": "ecs::SystemWorld", "to": "ecs::system::CameraSystem", "kind": "owns", "via": "SystemWorld.camera" },
    { "from": "ecs::SystemWorld", "to": "ecs::system::InputSystem", "kind": "owns", "via": "SystemWorld.input" },
    { "from": "ecs::SystemWorld", "to": "ecs::system::LightSystem", "kind": "owns", "via": "SystemWorld.light" },
    { "from": "ecs::SystemWorld", "to": "ecs::system::TextSystem", "kind": "owns", "via": "SystemWorld.text" },
    { "from": "ecs::SystemWorld", "to": "ecs::system::TextureSystem", "kind": "owns", "via": "SystemWorld.texture" },

    { "from": "ecs::SystemWorld", "to": "ecs::World", "kind": "uses", "via": "tick/process_commands/prepare_render accept &mut World" },
    { "from": "ecs::SystemWorld", "to": "graphics::VisualWorld", "kind": "uses", "via": "tick/process_commands/prepare_render accept &mut VisualWorld" },
    { "from": "ecs::SystemWorld", "to": "engine::user_input::InputState", "kind": "uses", "via": "tick(..., input, ...)" },
    { "from": "ecs::SystemWorld", "to": "graphics::RenderAssets", "kind": "uses", "via": "prepare_render(..., render_assets, uploader)" },

    { "from": "ecs::system::TransformSystem", "to": "ecs::system::CameraSystem", "kind": "calls", "via": "transform_changed(... camera_system, ...)" },
    { "from": "ecs::system::TransformSystem", "to": "ecs::system::LightSystem", "kind": "calls", "via": "transform_changed(... light_system, ...)" },
    { "from": "ecs::system::TransformSystem", "to": "ecs::system::CollisionSystem", "kind": "calls", "via": "transform_changed(... collision_system, ...)" },
    { "from": "ecs::system::TransformSystem", "to": "graphics::VisualWorld", "kind": "uses", "via": "sync transforms into VisualWorld instances" },

    { "from": "ecs::system::LightSystem", "to": "ecs::system::TransformSystem", "kind": "uses", "via": "world_position() for light placement" },
    { "from": "ecs::system::LightSystem", "to": "graphics::VisualWorld", "kind": "uses", "via": "upsert_point_light / set_ambient_light" },

    { "from": "ecs::system::CameraSystem", "to": "ecs::system::TransformSystem", "kind": "uses", "via": "world transforms for camera view" },
    { "from": "ecs::system::CameraSystem", "to": "graphics::VisualWorld", "kind": "uses", "via": "writes camera data / active camera into VisualWorld" },

    { "from": "ecs::system::RenderableSystem", "to": "ecs::system::TransformSystem", "kind": "uses", "via": "derives world transforms for renderables" },
    { "from": "ecs::system::RenderableSystem", "to": "graphics::VisualWorld", "kind": "uses", "via": "creates/upserts VisualWorld instances" },
    { "from": "ecs::system::RenderableSystem", "to": "graphics::RenderAssets", "kind": "uses", "via": "CPU mesh lookup + derived meshes" },
    { "from": "ecs::system::RenderableSystem", "to": "graphics::primitives", "kind": "uses", "via": "Renderable/Material/Transform types" },

    { "from": "ecs::system::TextureSystem", "to": "graphics::VisualWorld", "kind": "uses", "via": "attaches texture handles to instances" },

    { "from": "ecs::system::TextSystem", "to": "ecs::World", "kind": "uses", "via": "spawns glyph component subtrees" },
    { "from": "ecs::system::TextSystem", "to": "graphics::VisualWorld", "kind": "uses", "via": "register_text signature accepts &mut VisualWorld" },

    { "from": "ecs::system::GLTFSystem", "to": "graphics::mesh", "kind": "uses", "via": "imports CpuMesh/CpuVertex" },
    { "from": "ecs::system::GLTFSystem", "to": "graphics::RenderAssets", "kind": "uses", "via": "register_imported_mesh()" },
    { "from": "ecs::system::GLTFSystem", "to": "ecs::system::TextureSystem", "kind": "calls", "via": "flush_imports(..., texture_system, ...) registers cached textures" },

    { "from": "ecs::system::OpenXRSystem", "to": "ecs::system::TransformSystem", "kind": "uses", "via": "world transforms for XR rig/cameras" },
    { "from": "ecs::system::OpenXRSystem", "to": "graphics::VulkanoRenderer", "kind": "uses", "via": "render_xr copies/blits rendered images" },
    { "from": "ecs::system::OpenXRSystem", "to": "graphics::XRSwapchain", "kind": "uses", "via": "XR swapchain management" },
    { "from": "ecs::system::OpenXRSystem", "to": "graphics::XrVulkanGraphics", "kind": "uses", "via": "OpenXR Vulkan session creation" },
    { "from": "ecs::system::OpenXRSystem", "to": "graphics::VisualWorld", "kind": "uses", "via": "reads camera state / writes active XR camera" },

    { "from": "ecs::system::CollisionSystem", "to": "ecs::system::TransformSystem", "kind": "uses", "via": "world_position fallback / transform updates" },

    { "from": "ecs::system::InputSystem", "to": "engine::user_input::InputState", "kind": "uses", "via": "reads key/mouse state" },
    { "from": "ecs::system::InputSystem", "to": "utils::math", "kind": "uses", "via": "quat/vec math" },

    { "from": "graphics::VulkanoRenderer", "to": "graphics::VisualWorld", "kind": "uses", "via": "render_visual_world snapshot" }
  ]
}
